{
  "eth": {
    "current_price": {
      "usd": 2826.91,
      "cny": 19642.49
    },
    "changes": {
      "1h": -6.12,
      "24h": -6.12,
      "7d": -4.12,
      "30d": -4.82,
      "1y": -9.23
    },
    "volume_24h": {
      "usd": 32375002381.10888,
      "cny": 224954335483
    },
    "market_cap": {
      "usd": 340578493005.95087,
      "cny": 2366474222060
    }
  },
  "btc": {
    "current_price": {
      "usd": 84331,
      "cny": 585966
    },
    "changes": {
      "1h": -5.9,
      "24h": -5.9,
      "7d": -5.72,
      "30d": -4.62,
      "1y": -18.69
    },
    "volume_24h": {
      "usd": 62582950003.412605,
      "cny": 434851725720
    },
    "market_cap": {
      "usd": 1682158447459.49,
      "cny": 11688319322954
    }
  },
  "doge": {
    "current_price": {
      "usd": 0.116621,
      "cny": 0.810332
    },
    "changes": {
      "1h": -6.78,
      "24h": -6.78,
      "7d": -6.07,
      "30d": -5.39,
      "1y": -64.06
    },
    "volume_24h": {
      "usd": 1568697947.3741207,
      "cny": 10899976377
    },
    "market_cap": {
      "usd": 19650730077.80101,
      "cny": 136541578321
    }
  },
  "last_updated": "2026/01/30 02:06:49"
}