{
  "eth": {
    "current_price": {
      "usd": 2049.85,
      "cny": 14161.68
    },
    "changes": {
      "1h": 6.64,
      "24h": 6.64,
      "7d": -0.53,
      "30d": -38.93,
      "1y": -23.39
    },
    "volume_24h": {
      "usd": 18751449106.91394,
      "cny": 129547050657
    },
    "market_cap": {
      "usd": 247553410752.51944,
      "cny": 1710257914475
    }
  },
  "btc": {
    "current_price": {
      "usd": 68825,
      "cny": 475486
    },
    "changes": {
      "1h": 4.7,
      "24h": 4.7,
      "7d": -2.41,
      "30d": -29.05,
      "1y": -28.72
    },
    "volume_24h": {
      "usd": 44414362919.43772,
      "cny": 306842103409
    },
    "market_cap": {
      "usd": 1375960838581.1614,
      "cny": 9505995136849
    }
  },
  "doge": {
    "current_price": {
      "usd": 0.096965,
      "cny": 0.669895
    },
    "changes": {
      "1h": 5.9,
      "24h": 5.9,
      "7d": -1.57,
      "30d": -34.12,
      "1y": -63.03
    },
    "volume_24h": {
      "usd": 918378867.5307115,
      "cny": 6344736879
    },
    "market_cap": {
      "usd": 16378306210.417599,
      "cny": 113151605619
    }
  },
  "last_updated": "2026/02/14 05:55:41"
}