{
  "eth": {
    "current_price": {
      "usd": 4316.03,
      "cny": 30775
    },
    "changes": {
      "1h": -5.22,
      "24h": -5.22,
      "7d": -10.63,
      "30d": 13.36,
      "1y": 70.81
    },
    "volume_24h": {
      "usd": 37436556581.31006,
      "cny": 266937446864
    },
    "market_cap": {
      "usd": 521251419157.1053,
      "cny": 3716728666057
    }
  },
  "btc": {
    "current_price": {
      "usd": 108270,
      "cny": 772021
    },
    "changes": {
      "1h": -4.23,
      "24h": -4.23,
      "7d": -7.33,
      "30d": -8.12,
      "1y": 82.42
    },
    "volume_24h": {
      "usd": 46342856262.62469,
      "cny": 330448492054
    },
    "market_cap": {
      "usd": 2159194767742.2502,
      "cny": 15396173490229
    }
  },
  "doge": {
    "current_price": {
      "usd": 0.214757,
      "cny": 1.53
    },
    "changes": {
      "1h": -4.22,
      "24h": -4.22,
      "7d": -10.75,
      "30d": -2.52,
      "1y": 113.92
    },
    "volume_24h": {
      "usd": 2261355812.3447976,
      "cny": 16110647815
    },
    "market_cap": {
      "usd": 32358096004.75588,
      "cny": 230529793615
    }
  },
  "last_updated": "2025/08/29 23:13:10"
}