{
  "eth": {
    "current_price": {
      "usd": 2054.97,
      "cny": 14164.11
    },
    "changes": {
      "1h": -3.64,
      "24h": -3.64,
      "7d": -5.22,
      "30d": 1.26,
      "1y": 14.43
    },
    "volume_24h": {
      "usd": 17366772089.037148,
      "cny": 119702414251
    },
    "market_cap": {
      "usd": 247884733738.84454,
      "cny": 1708573184036
    }
  },
  "btc": {
    "current_price": {
      "usd": 66886,
      "cny": 461017
    },
    "changes": {
      "1h": -2.62,
      "24h": -2.62,
      "7d": -6.2,
      "30d": -2.87,
      "1y": -18.95
    },
    "volume_24h": {
      "usd": 43863959978.007195,
      "cny": 302335783829
    },
    "market_cap": {
      "usd": 1337869540957.6519,
      "cny": 9221370722777
    }
  },
  "doge": {
    "current_price": {
      "usd": 0.090178,
      "cny": 0.621561
    },
    "changes": {
      "1h": -3.52,
      "24h": -3.52,
      "7d": -6.06,
      "30d": -3.65,
      "1y": -45.09
    },
    "volume_24h": {
      "usd": 1115936548.1649423,
      "cny": 7691705702
    },
    "market_cap": {
      "usd": 13853492949.65839,
      "cny": 95486603510
    }
  },
  "last_updated": "2026/04/02 15:51:27"
}