{
  "eth": {
    "current_price": {
      "usd": 4187.65,
      "cny": 29788
    },
    "changes": {
      "1h": -2.28,
      "24h": -2.28,
      "7d": -7.44,
      "30d": -12.28,
      "1y": 58.14
    },
    "volume_24h": {
      "usd": 46317229106.48931,
      "cny": 329468226959
    },
    "market_cap": {
      "usd": 506011795761.7771,
      "cny": 3599412408428
    }
  },
  "btc": {
    "current_price": {
      "usd": 112734,
      "cny": 801921
    },
    "changes": {
      "1h": -1.42,
      "24h": -1.42,
      "7d": -2.31,
      "30d": -2.28,
      "1y": 78.02
    },
    "volume_24h": {
      "usd": 67468019368.73155,
      "cny": 479926389201
    },
    "market_cap": {
      "usd": 2248601292052.76,
      "cny": 15995179774728
    }
  },
  "doge": {
    "current_price": {
      "usd": 0.240509,
      "cny": 1.71
    },
    "changes": {
      "1h": -2.9,
      "24h": -2.9,
      "7d": -10.44,
      "30d": 1.95,
      "1y": 122.25
    },
    "volume_24h": {
      "usd": 4293923515.40372,
      "cny": 30529457157
    },
    "market_cap": {
      "usd": 36392993129.31996,
      "cny": 258751307648
    }
  },
  "last_updated": "2025/09/23 13:57:30"
}