{
  "eth": {
    "current_price": {
      "usd": 4207.74,
      "cny": 29937
    },
    "changes": {
      "1h": 0.06,
      "24h": 0.06,
      "7d": -7,
      "30d": -11.86,
      "1y": 58.9
    },
    "volume_24h": {
      "usd": 37223898416.20098,
      "cny": 264838570559
    },
    "market_cap": {
      "usd": 508072463593.98395,
      "cny": 3614806366984
    }
  },
  "btc": {
    "current_price": {
      "usd": 113026,
      "cny": 804155
    },
    "changes": {
      "1h": 0,
      "24h": 0,
      "7d": -2.05,
      "30d": -2.02,
      "1y": 78.48
    },
    "volume_24h": {
      "usd": 55980839813.9595,
      "cny": 398291297937
    },
    "market_cap": {
      "usd": 2252417256750.8564,
      "cny": 16025450773295
    }
  },
  "doge": {
    "current_price": {
      "usd": 0.242078,
      "cny": 1.72
    },
    "changes": {
      "1h": 1.36,
      "24h": 1.36,
      "7d": -9.85,
      "30d": 2.62,
      "1y": 123.7
    },
    "volume_24h": {
      "usd": 3481858541.3348165,
      "cny": 24739119999
    },
    "market_cap": {
      "usd": 36567940742.9929,
      "cny": 259820628384
    }
  },
  "last_updated": "2025/09/23 15:45:36"
}