{
  "eth": {
    "current_price": {
      "usd": 4265.21,
      "cny": 30423
    },
    "changes": {
      "1h": -1.28,
      "24h": -1.28,
      "7d": -2.47,
      "30d": 9.05,
      "1y": 91.8
    },
    "volume_24h": {
      "usd": 15928972221.691732,
      "cny": 113618584290
    },
    "market_cap": {
      "usd": 514652887289.76514,
      "cny": 3670929400901
    }
  },
  "btc": {
    "current_price": {
      "usd": 110184,
      "cny": 785925
    },
    "changes": {
      "1h": -0.95,
      "24h": -0.95,
      "7d": 1.29,
      "30d": -6.2,
      "1y": 104.33
    },
    "volume_24h": {
      "usd": 24385052515.623753,
      "cny": 173934712829
    },
    "market_cap": {
      "usd": 2194338192214.683,
      "cny": 15651866366408
    }
  },
  "doge": {
    "current_price": {
      "usd": 0.213711,
      "cny": 1.52
    },
    "changes": {
      "1h": -1.35,
      "24h": -1.35,
      "7d": -0.98,
      "30d": -3.92,
      "1y": 131.05
    },
    "volume_24h": {
      "usd": 1168017905.428031,
      "cny": 8307420845
    },
    "market_cap": {
      "usd": 32224933566.26711,
      "cny": 229196901520
    }
  },
  "last_updated": "2025/09/07 03:35:04"
}