{
  "eth": {
    "current_price": {
      "usd": 4401.84,
      "cny": 31614
    },
    "changes": {
      "1h": -3.57,
      "24h": -3.57,
      "7d": 3.19,
      "30d": 26.42,
      "1y": 69.81
    },
    "volume_24h": {
      "usd": 39135649831.21425,
      "cny": 281072104793
    },
    "market_cap": {
      "usd": 530907106584.8597,
      "cny": 3812973044812
    }
  },
  "btc": {
    "current_price": {
      "usd": 117743,
      "cny": 845645
    },
    "changes": {
      "1h": -0.31,
      "24h": -0.31,
      "7d": 1.06,
      "30d": -1.43,
      "1y": 99.96
    },
    "volume_24h": {
      "usd": 33471974415.631123,
      "cny": 240399920205
    },
    "market_cap": {
      "usd": 2342403170138.9756,
      "cny": 16823433484897
    }
  },
  "doge": {
    "current_price": {
      "usd": 0.227482,
      "cny": 1.63
    },
    "changes": {
      "1h": -0.4,
      "24h": -0.4,
      "7d": -5.53,
      "30d": 3.85,
      "1y": 126.73
    },
    "volume_24h": {
      "usd": 3625225167.1316266,
      "cny": 25976196017
    },
    "market_cap": {
      "usd": 34231874302.597675,
      "cny": 245285143938
    }
  },
  "last_updated": "2025/08/16 22:13:02"
}